markdown_formatter/__init__.py
markdown_formatter/cli.py
markdown_formatter/docdata.py
markdown_formatter/renderer.py
markdown_formatter/types.py
markdown_formatter/utils.py
markdown_formatter-0.0.4.dist-info/entry_points.txt
markdown_formatter-0.0.4.dist-info/WHEEL
markdown_formatter-0.0.4.dist-info/METADATA
markdown_formatter-0.0.4.dist-info/RECORD
